README.md
ete_robinson_foulds.py
setup.py
ete_robinson_foulds.egg-info/PKG-INFO
ete_robinson_foulds.egg-info/SOURCES.txt
ete_robinson_foulds.egg-info/dependency_links.txt
ete_robinson_foulds.egg-info/requires.txt
ete_robinson_foulds.egg-info/top_level.txt